{
  "name": "Vera Conner",
  "age": 38,
  "address": {
    "street": "Pocu Plaza",
    "city": "Bomputav",
    "state": "UT",
    "zip": "84436"
  },
  "contact": {
    "phone": "(841) 963-8534",
    "servicePhone": "800911174"
  },
  "birthday": "1983-12-05T11:28:23.819Z",
  "ip": "187.251.231.144",
  "foo": "bar",
  "profile": {
    "about": "Beifudom ene fesmeno abmim kewde gocupbo puage ipuwogpa tev jimmasu bume aw zitu. Ehe ralmauti fuj sigjep haefadi hilro lidjurop ne ojsul an ak bibuf jajtaw vik. Jif eteva encu ihe kaizo pijuheeke wi kujzid togsaznak ta lic pih unic ji ifu foracep efsip. Waejsa re daav zodimri wiv kiebu cew sa vir nejcuwjo ma zovpuleb remwaheho cog weos tetol nagrif iwi. Or elorugca viuson mu keginjep ethiur bi hiwjovdi uk av ojuciz ezuisdu ojic.",
    "bio": "Suzekefid omco buzik poknidvi jenepa jesow zibiro coj afo hu lo reasce zotu kuari lu nianfo cosnica. Oreafwem woloh urmar nebof tahigaw pevir wemfujan kam lisdobazo bajas ufulu wav ca ajijuzag. No zajfo ezu lizevura limmassa sora neticjo upa rigjo futicubef gi acsaku rom tetverna oratu hewaati."
  },
  "apiKey": "f4718f8280fb51182887d88a2c1a605d56fc74f50fc13a02660861d7c9999310",
  "currency": {
    "code": "TRY",
    "name": "Turkey Lira"
  }
}