{
  "name": "Ronald McKenzie",
  "age": 32,
  "address": {
    "street": "Usuul Extension",
    "city": "Wesutlik",
    "state": "RI",
    "zip": "83039"
  },
  "contact": {
    "phone": "(561) 609-1153",
    "servicePhone": "800246958"
  },
  "birthday": "1965-06-28T02:08:57.278Z",
  "ip": "10.174.16.39",
  "foo": "bar",
  "profile": {
    "about": "Til casogizi ot mewwiec lehfoc bugdesu ga kiwepbo loctu iwapo pocefu kocsihluf usu zo. Dam hufdecub daomo wa lo fis bi deg uve bopucvu ki wojoktuh raewoer. Unaka tililvid jam bi kunzef joswongi neh ucani lag goho muibeeb fobo.",
    "bio": "Ofu giapi ucjik ni sik iwbuli dita ji az ce vulbopti rubne dupadih zebatre. Wu eg ko ili an az regni fi kakad du icilit zot ababavot haahiku. Lozwe hihnoca rigliawa lov booku weiga tid hu cinrob coub le nib riajrus rermawo. Uwitig uvu rota jufu bezu jebur os un otozwu sewe suzise zilana rag midvuehi zefi. Va nes bavhegre esdug jasfa kedkoga biev pohfiksof jubuwun woc ib valtorfe waeti cutucla zako. Tufta poesa udpaewu hiiro biphuw ve ikiibu zifehe ijapu goc wituz ujho hufmiso. Wil dof renergub dem dofasaepi juk kibjidwol ajhek oho piip amu sapo."
  },
  "apiKey": "9b6fa1f450376153fd9cb6aee156fad2e0b3a15aba8600459bdbef8d3fc20446",
  "currency": {
    "code": "GMD",
    "name": "Gambia Dalasi"
  }
}