{
  "name": "Brent Ramsey",
  "age": 38,
  "address": {
    "street": "Luru Pass",
    "city": "Lidfaghoh",
    "state": "TX",
    "zip": "36082"
  },
  "contact": {
    "phone": "(432) 354-2482",
    "servicePhone": "800732866"
  },
  "birthday": "1976-01-18T16:52:02.221Z",
  "ip": "206.55.216.128",
  "foo": "bar",
  "profile": {
    "about": "Pimpegnew huepata fu ficdaje evogicro uge hapgobu rekralapi tigsecni we ludirpib toitja womu rosom ivaace bomi. Sobab vun elzouk suppi rusu ma faci fem evwe gavkepra zinlo wugelieg. Aro awuawuh azdame ri alepi debod zagvur wopenefu zedurwu mi fu lajvoso uze edme. Rezmod ozpimaf ri behpej jaukibu dikug de saz deelileh ho cuwimbu ob evono ezejegnot itno. Itafede su as upuzen lisahe ji jator sucifan utreke pu zivzifmu azilan famenveg co rokig bi bicot kikpasjok. Hiw luopuki givifgek fugevow zeopo mujo nacdil fibew ilih fitit mawujola ipuf doslazu zehgor baeta gi tom mir.",
    "bio": "Paeccum kewceg hislome opakag rela waguda viimano jokiwjes hozsiov sir kufilu dafzinet kaj erisi egvom vij jo nu. Kif dibop efiakatos nihwuwur efekev vu kij veskewvez jo vunbun mu lekugef. Denjuthiz hirlis de fudo nesol miur cem jimuce likmun dis ara buzgobsid cabo vilfih kemosvoj."
  },
  "apiKey": "b01fe299cb5f1a729d4b7800313920b78235ce495439c12a26dba0319962e3ff",
  "currency": {
    "code": "IMP",
    "name": "Isle of Man Pound"
  }
}