{
  "name": "Nettie Parks",
  "age": 55,
  "address": {
    "street": "Cuuk River",
    "city": "Imcuewo",
    "state": "KS",
    "zip": "17388"
  },
  "contact": {
    "phone": "(532) 749-4016",
    "servicePhone": "800539724"
  },
  "birthday": "1973-04-24T11:14:30.861Z",
  "ip": "156.215.140.223",
  "foo": "bar",
  "profile": {
    "about": "Kavjuztos titepa atezehzog ubzo sedefu rahetu kuehu ez meol pegniwo fa te. Lu bedzuvu oci vak vabkukni ropasweg efwe wo da vir lef pumuc fa loja gujevoh nob mob nop. Kokeg mepcocpuf ustulbo zep zomte dunefmon jaoco luwigvi zivigje ilja dajim nibit singum. Ebo er nejdekhi ron neuj jufefawu mo ipunuza jacicu levapuve runefava le nac. Ludha piwgut loaka ico kej bied ozoreb ju wi kalu eb ogevera bo so ki akualerap lefabhe. Waojago ujopu udlasot hihzarom puilcob cis liezpur vikuvosin enatoj ewopiwit bewod uluzeid cuwbu ovi jiz vesji isnuj ricekir. Ebici kadmaszit lo hej uckog fuane hapugje di mem tiho ces luvusgis vamagli zansik fe kibisole.",
    "bio": "Peg jubebab oceka imijukez uv huni mikat esguone ufi ni fahjep puzes ovu rojwapeg hahab cilgomod wobi. Sep ite fa dipva esaezdu deje ta fefnij mi zuf bu pusez molmen faviva opatej ewu rowsukfe. Iz ole ec kamam ed iplug peg kozcemi cad pik hofiwlab sum ru tit fufawe esdig kekadtum. Umozoj ezobupsoz ic si towdubfih jutduku vegikic nedajsi solipi od makbetnu ke hit hucubo nozinita. Gacufhe zi la lohluz gida epu motusaujo sudanlew lepokzul mu pic gavto fu eraahi tocu mimastur mah."
  },
  "apiKey": "65e8e17fb1669a7cf00cb20af534a2386faee5af91630af7a0361f16e87114cc",
  "currency": {
    "code": "MZN",
    "name": "Mozambique Metical"
  }
}